axmp_ai_agent_studio/__init__.py
axmp_ai_agent_studio/db/__init__.py
axmp_ai_agent_studio/db/agent_profile_repository.py
axmp_ai_agent_studio/db/base_repository.py
axmp_ai_agent_studio/entity/__init__.py
axmp_ai_agent_studio/entity/agent_profile.py
axmp_ai_agent_studio/entity/base_model.py
axmp_ai_agent_studio/exception/__init__.py
axmp_ai_agent_studio/exception/db_exceptions.py
axmp_ai_agent_studio/exception/servivce_exception.py
axmp_ai_agent_studio/main.py
axmp_ai_agent_studio/router/__init__.py
axmp_ai_agent_studio/router/agent_profile_router.py
axmp_ai_agent_studio/router/healthy_router.py
axmp_ai_agent_studio/router/mcp_profiles_router.py
axmp_ai_agent_studio/scheme/__init__.py
axmp_ai_agent_studio/scheme/agent_profile_dto.py
axmp_ai_agent_studio/scheme/agent_profile_query.py
axmp_ai_agent_studio/scheme/base_search_query.py
axmp_ai_agent_studio/scheme/list_model.py
axmp_ai_agent_studio/scheme/response_model.py
axmp_ai_agent_studio/service/__init__.py
axmp_ai_agent_studio/service/agent_service.py
axmp_ai_agent_studio/setting.py
axmp_ai_agent_studio/util/depends_utils.py
axmp_ai_agent_studio/util/list_utils.py
axmp_ai_agent_studio/util/search_utils.py
axmp_ai_agent_studio/util/time_utils.py
axmp_ai_agent_studio-0.1.0.dist-info/METADATA
axmp_ai_agent_studio-0.1.0.dist-info/WHEEL
axmp_ai_agent_studio-0.1.0.dist-info/RECORD
