Metadata-Version: 2.3
Name: axmp-ai-agent-studio
Version: 0.1.0
Summary: This is a backend service for the AI Agent Studio
Author: Kilsoo Kang
Author-email: kilsoo75@gmail.com
Maintainer: Kilsoo Kang
Maintainer-email: kilsoo75@gmail.com
Requires-Python: >=3.12,<4.0
Classifier: Programming Language :: Python :: 3
Classifier: Programming Language :: Python :: 3.12
Classifier: Programming Language :: Python :: 3.13
Requires-Dist: colorlog (>=6.9.0,<7.0.0)
Requires-Dist: fastapi (>=0.115.11,<0.116.0)
Requires-Dist: motor (>=3.7.0,<4.0.0)
Requires-Dist: pydantic (>=2.10.6)
Requires-Dist: pydantic-settings (>=2.9.1,<3.0.0)
Requires-Dist: pyjwt (>=2.10.1,<3.0.0)
Requires-Dist: pymongo (>=4.12.0,<5.0.0)
Requires-Dist: python-dotenv (>=1.0.1,<2.0.0)
Requires-Dist: sse-starlette (>=2.1.0,<2.2.0)
Requires-Dist: starlette (>=0.46.2,<0.47.0)
Requires-Dist: starlette-csrf (>=3.0.0,<4.0.0)
Requires-Dist: zmp-authentication-provider (>=0.1.0,<0.2.0)
Project-URL: Bug Tracker, https://github.com/cloudz-mp/axmp-ai-agent-studio.git/issues
Project-URL: Documentation, https://github.com/cloudz-mp/axmp-ai-agent-studio.git
Project-URL: Homepage, https://github.com/cloudz-mp
Project-URL: Repository, https://github.com/cloudz-mp/axmp-ai-agent-studio.git
